ttutils/__init__.py
ttutils/compress.py
ttutils/concurrency.py
ttutils/config.py
ttutils/datetime.py
ttutils/helpers.py
ttutils/logging.py
ttutils/py.typed
ttutils/safe_types.py
ttutils/stats.py
ttutils-0.10.dist-info/licenses/LICENSE
ttutils-0.10.dist-info/METADATA
ttutils-0.10.dist-info/WHEEL
ttutils-0.10.dist-info/top_level.txt
ttutils-0.10.dist-info/RECORD
